requirejs/__init__.py
requirejs/env.js
requirejs/execjs.py
requirejs/r.js
requirejs-0.2.2.dist-info/LICENSE
requirejs-0.2.2.dist-info/METADATA
requirejs-0.2.2.dist-info/WHEEL
requirejs-0.2.2.dist-info/top_level.txt
requirejs-0.2.2.dist-info/RECORD
